ecgai_drawing/__init__.py
ecgai_drawing/create_ecg_plot.py
ecgai_drawing/ecg_grid_plotter.py
ecgai_drawing/ecg_plot_image.py
ecgai_drawing/ecg_plotter.py
ecgai_drawing/enums/__init__.py
ecgai_drawing/enums/artifact.py
ecgai_drawing/enums/color_style.py
ecgai_drawing/enums/ecg_lead_name.py
ecgai_drawing/enums/enum_ordered_base.py
ecgai_drawing/enums/show_grid.py
ecgai_drawing/grid_images/bw_six_x_two.png
ecgai_drawing/grid_images/colour_six_x_two.png
ecgai_drawing/images.py
ecgai_drawing/models/__init__.py
ecgai_drawing/models/ecg_lead.py
ecgai_drawing/models/ecg_leads.py
ecgai_drawing/models/model_base.py
ecgai_drawing-0.1.15.dist-info/METADATA
ecgai_drawing-0.1.15.dist-info/WHEEL
ecgai_drawing-0.1.15.dist-info/RECORD
