Metadata-Version: 2.1
Name: ecgai-drawing
Version: 0.1.15
Summary: 
Author: RobC
Author-email: rob.clapham@gmail.com
Requires-Python: >=3.9,<3.12
Classifier: Programming Language :: Python :: 3
Classifier: Programming Language :: Python :: 3.9
Classifier: Programming Language :: Python :: 3.10
Classifier: Programming Language :: Python :: 3.11
Requires-Dist: aenum (>=3.1.11,<4.0.0)
Requires-Dist: matplotlib (>=3.5.3,<4.0.0)
Requires-Dist: numpy (>=1.23.2,<2.0.0)
Requires-Dist: opencv-python (>=4.6.0,<5.0.0)
Requires-Dist: pydantic (>=1.9.2,<2.0.0)
Requires-Dist: scikit-image (>=0.20.0,<0.21.0)
Requires-Dist: scipy (>=1.9.0,<2.0.0)
Requires-Dist: timer (>=0.2.2,<0.3.0)
